prettytable_extras.py
setup.py
prettytable_extras.egg-info/PKG-INFO
prettytable_extras.egg-info/SOURCES.txt
prettytable_extras.egg-info/dependency_links.txt
prettytable_extras.egg-info/requires.txt
prettytable_extras.egg-info/top_level.txt