Metadata-Version: 1.1
Name: prettytable-extras
Version: 0.1.0
Summary: An extension to the excellent prettytable Python library
Home-page: https://github.com/moul/prettytable-extras
Author: Manfred Touron
Author-email: m@42.am
License: BSD (3 clause)
Platform: UNKNOWN
Classifier: Programming Language :: Python
Classifier: Programming Language :: Python :: 2.7
Classifier: License :: OSI Approved :: BSD License
Classifier: Topic :: Text Processing
